<?xml version="1.0" encoding="UTF-8"?>
<?xml-stylesheet type="text/css" href = "xmlstyle.css" ?>
<setlist>  
    <songInfo>
        <title> In The Party 
        </title>
        <artist> Flo Milli  
        </artist>
        <genre> Rap
        </genre>
        <year> 2020 
        </year>    
    </songInfo>
    
    <songInfo>
        <title> O Bêbado e a Equilibrista
        </title>
        <artist> Elis Regina  
        </artist>
        <genre> Bossa Nova
        </genre>
        <year> 1979
        </year>    
    </songInfo>
    
    <songInfo>
        <title> Liquid Smooth 
        </title>
        <artist> Mitski  
        </artist>
        <genre> Alternative/Indie 
        </genre>
        <year> 2012 
        </year>    
    </songInfo>
    
    <songInfo>
        <title> Summer Breeze
        </title>
        <artist> Seals and Crofts  
        </artist>
        <genre> Rock
        </genre>
        <year> 1972 
        </year>    
    </songInfo>
    
    <songInfo>
        <title> Hips Don't Lie
        </title>
        <artist> Shakira  
        </artist>
        <genre> Pop 
        </genre>
        <year> 2005 
        </year>    
    </songInfo>
    
    <songInfo>
        <title> Another One Bites the Dust 
        </title>
        <artist> Queen  
        </artist>
        <genre> Rock 
        </genre>
        <year> 1980 
        </year>    
    </songInfo>
    
    <songInfo>
        <title> Supermodel
        </title>
        <artist> SZA  
        </artist>
        <genre> Neo soul
        </genre>
        <year> 2017 
        </year>    
    </songInfo>
    
    <songInfo>
        <title> XS
        </title>
        <artist> Rina Sawayama  
        </artist>
        <genre> Pop
        </genre>
        <year> 2020 
        </year>    
    </songInfo>
    
    <songInfo>
        <title> Pon de Replay 
        </title>
        <artist> Rihanna   
        </artist>
        <genre> Dance Pop
        </genre>
        <year> 2005 
        </year>    
    </songInfo>
    
    <songInfo>
        <title> Hayloft
        </title>
        <artist> Mother Mother  
        </artist>
        <genre> Alternative/Indie
        </genre>
        <year> 2008 
        </year>    
    </songInfo>
    
</setlist>